[
    {
        "id": 1,
        "groupID": 1,
        "name": "General",
        "dateTime": "Tue, 06 Sep 2022 07:55:50 GMT"
    },
    {
        "id": 2,
        "groupID": 1,
        "name": "Assignment",
        "dateTime": "Tue, 06 Sep 2022 07:55:50 GMT"
    },
    {
        "id": 3,
        "groupID": 2,
        "name": "Jazz Dance",
        "dateTime": "Tue, 06 Sep 2022 07:55:50 GMT"
    },
    {
        "id": 4,
        "groupID": 2,
        "name": "Hip Hop",
        "dateTime": "Tue, 06 Sep 2022 07:55:50 GMT"
    },
    {
        "id": 5,
        "groupID": 2,
        "name": "House",
        "dateTime": "Tue, 06 Sep 2022 07:55:50 GMT"
    },
    {
        "id": 6,
        "groupID": 3,
        "name": "General",
        "dateTime": "Tue, 06 Sep 2022 07:55:50 GMT"
    },
    {
        "id": 7,
        "groupID": 3,
        "name": "Software Eng",
        "dateTime": "Tue, 06 Sep 2022 07:55:50 GMT"
    },
    {
        "id": 8,
        "groupID": 3,
        "name": "Soft Frame",
        "dateTime": "Tue, 06 Sep 2022 07:55:50 GMT"
    },
    {
        "id": 9,
        "groupID": 3,
        "name": "Web App Dev",
        "dateTime": "Tue, 06 Sep 2022 07:55:50 GMT"
    },
    {
        "id": 10,
        "groupID": 4,
        "name": "General",
        "dateTime": "Tue, 06 Sep 2022 07:55:50 GMT"
    },
    {
        "id": 11,
        "groupID": 5,
        "name": "Discussion",
        "dateTime": "Tue, 06 Sep 2022 07:55:50 GMT"
    },
    {
        "id": 12,
        "groupID": 6,
        "name": "Events",
        "dateTime": "Tue, 06 Sep 2022 07:55:50 GMT"
    },
    {
        "id": 13,
        "groupID": 7,
        "name": "Adopt",
        "dateTime": "Tue, 06 Sep 2022 07:55:50 GMT"
    }
]
